query_farm_sql_scan_planning/__init__.py
query_farm_sql_scan_planning/planner.py
query_farm_sql_scan_planning/py.typed
query_farm_sql_scan_planning/test_planner.py
query_farm_sql_scan_planning-0.1.6.dist-info/METADATA
query_farm_sql_scan_planning-0.1.6.dist-info/WHEEL
query_farm_sql_scan_planning-0.1.6.dist-info/licenses/LICENSE
query_farm_sql_scan_planning-0.1.6.dist-info/RECORD
