Metadata-Version: 2.3
Name: query-farm-sql-scan-planning
Version: 0.1.6
Summary: A Python library for intelligent file filtering using SQL expressions and metadata-based scan planning. This library enables efficient data lake query optimization by determining which files need to be scanned based on their statistical metadata.
Project-URL: Repository, https://github.com/query-farm/python-sql-scan-planning.git
Project-URL: Issues, https://github.com/query-farm/python-sql-scan-planning/issues
Author-email: Rusty Conover <rusty@conover.me>
Keywords: predicate pushdown,scan planning,sql,sql scan planning
Classifier: Development Status :: 4 - Beta
Classifier: Intended Audience :: Developers
Classifier: Programming Language :: Python :: 3.11
Classifier: Topic :: Database
Classifier: Topic :: Database :: Database Engines/Servers
Requires-Python: >=3.11
Requires-Dist: duckdb>=1.0.0
Requires-Dist: pyarrow>=18.0.0
Requires-Dist: sqlglot>=26.33.0
